xy_list/List.py
xy_list/ModuleData.py
xy_list/Resource.py
xy_list/__init__.py
xy_list/utils.py
xy_list/execute/Main.py
xy_list/execute/__init__.py
xy_list-1.0.6.dist-info/LICENSE
xy_list-1.0.6.dist-info/METADATA
xy_list-1.0.6.dist-info/WHEEL
xy_list-1.0.6.dist-info/top_level.txt
xy_list-1.0.6.dist-info/RECORD
